{"ETH11": {"matching": {"distances": [35.0, 35.55555555555556, null, null, 35.0, null, 34.44444444444444, 35.0, 35.0, 35.55555555555556, null, null, 36.666666666666664, 35.0, null, 22.77777777777778, null, null, 34.44444444444444, null, 35.55555555555556, 34.44444444444444, 34.44444444444444, 35.0, null, 23.333333333333332, 35.0, null, 35.0, 35.0, null, null, 23.88888888888889, null, null, 24.444444444444443, null, 34.44444444444444, null], "indicators": ["KIV17", "KIV8", "KIV39", "KIV2", "KIV11", "KIV20", "KIV26", "KIV16", "KIV25", "KIV3", "KIV36", "KIV27", "KIV6", "KIV15", "KIV34", "KIV30", "KIV4", "KIV37", "KIV23", "KIV21", "KIV1", "KIV7", "KIV24", "KIV12", "KIV5", "KIV28", "KIV13", "KIV10", "KIV9", "KIV14", "KIV18", "KIV19", "KIV31", "KIV32", "KIV33", "KIV29", "KIV38", "KIV22", "KIV35"], "lib": ["NC Indigent PF sous DIU ou Implant gratuit", "Nouveaux cas TBC + d\u00c3\u00a9pist\u00c3\u00a9s (3 examens crachat)", "Nombre des visites \u00c3\u00a0\u00c2\u00a0 domicile r\u00c3\u00a9alis\u00c3\u00a9es", "Nouveau  cas suivi en observation", "Pilule + Inj (Nouv acceptantes) (si score qualit\u00c3\u00a9 >ou= \u00c3\u00a0\u00c2\u00a0 60%)", "PF Naturelle nouvelles inscrites couples autonomes", "CPN: 2\u00c3\u00a8me visite au 42e jour", "Indigent ayant re\u00c3\u00a7u Implants ou DIU", "Accouchements assist\u00c3\u00a9s avec 3 CPN (si score qualit\u00c3\u00a9 > ou = \u00c3\u00a0\u00c2\u00a0 60%)", "Patients graves r\u00c3\u00a9f\u00c3\u00a9r\u00c3\u00a9s et arriv\u00c3\u00a9 \u00c3\u00a0 l'h\u00c3\u00b4pital", "R\u00c3\u00a9union  d'analyse des donn\u00c3\u00a9es SNIS  y compris les donn\u00c3\u00a9es financi\u00c3\u00a8res  transmis  en annexe du SNIS  au BCZS  et rapport  SSR  transmis chez AAP", "Cas de VVS Refer\u00c3\u00a9s  et arriv\u00c3\u00a9es \u00c3\u00a0\u00c2\u00a0 l'Hopital", "Enfants compl\u00c3\u00a8tement vaccin\u00c3\u00a9s", "PF: Insertion d'implants ou DIU 2% par an", "Nbre des jeunes de 10 \u00c3\u00a0\u00c2\u00a0 24 ans ayant b\u00c3\u00a9n\u00c3\u00a9fici\u00c3\u00a9 le service  SSR", "Nombre d'Accouch\u00c3\u00a9es VIH+ mis sous traitement", "Enfant de 12 \u00c3\u00a0\u00c2\u00a0 59 mois inscrit \u00c3\u00a0\u00c2\u00a0la CPS 2", "R\u00c3\u00a9union  d'analyse des donn\u00c3\u00a9es SNIS  y compris les donn\u00c3\u00a9es financi\u00c3\u00a8res", "CPN 3 visites standards accomplies", "PF. Nombre des cas de Ligature et Vasectomie  r\u00c3\u00a9f\u00c3\u00a9r\u00c3\u00a9s et arriv\u00c3\u00a9 \u00c3\u00a0\u00c2\u00a0 l'h\u00c3\u00b4pital", "Consultations externes", "Femme enceinte ayant re\u00c3\u00a7u VAT 2+", "Accouchements assist\u00c3\u00a9s dans FOSA (si score qualit\u00c3\u00a9 >ou= \u00c3\u00a0\u00c2\u00a0 60%)", "Pilule + Inj (Anc acceptantes) (si score qualit\u00c3\u00a9 >ou= \u00c3\u00a0\u00c2\u00a0 60%)", "Enfant 12 \u00c3\u00a0\u00c2\u00a0 59 mois ayant r\u00c3\u00a9alis\u00c3\u00a9 4 visites standards (1/trim)", "Nombre des femmes enceintes test\u00c3\u00a9es au VIH", "NC Indigent nouvelle utilisatrice (Pillule+Injection)", "Grossesses \u00c3\u00a0\u00c2\u00a0 haut risque r\u00c3\u00a9f\u00c3\u00a9r\u00c3\u00a9e et arriv\u00c3\u00a9e", "Nombre de cas TBC trait\u00c3\u00a9s et BK- apr\u00c3\u00a8s 6 mois", "Indigent Ancienne  utilisatrice PF (Pillule -Injection)", "PF\u00c2\u00a0: Couple ayant adh\u00c3\u00a9r\u00c3\u00a9 aux m\u00c3\u00a9thodes PF modernes", "PF Naturelle nouvelles inscrites", "Nombre des nouveau-n\u00c3\u00a9s des femmes  VIH+ mis sous traitement", "Consultations externes (nvx cas de victime  des violences sexuelles trait\u00c3\u00a9s dans 72h)", "R\u00c3\u00a9unions d'\u00c3\u00a9change avec les jeunes et adolescents de 10 \u00c3\u00a0\u00c2\u00a024 ans organis\u00c3\u00a9 au CS", "Nombre des couples test\u00c3\u00a9s au VIH pour PTME ", "Promptitude, compl\u00c3\u00a9tude et correctitude \u00c3\u00a0\u00c2\u00a0 100% du SNIS transmis au BCZS", "CPN au 4\u00c3\u00a8me mois (d\u00c3\u00a9but T2)", "Nbre des jeunes de 18 \u00c3\u00a0\u00c2\u00a0 24 ans ayant  re\u00c3\u00a7u les contraceptifs modernes"]}, "lib": "New HIV/AIDS cases placed on ARV Therapy (ever started)"}, "ETH12": {"matching": {"distances": [35.0, 35.55555555555556, null, null, 35.0, null, 34.44444444444444, 35.0, 35.0, 35.55555555555556, null, null, 36.666666666666664, 35.0, null, 22.77777777777778, null, null, 34.44444444444444, null, 35.55555555555556, 34.44444444444444, 34.44444444444444, 35.0, null, 23.333333333333332, 35.0, null, 35.0, 35.0, null, null, 23.88888888888889, null, null, 24.444444444444443, null, 34.44444444444444, null], "indicators": ["KIV17", "KIV8", "KIV39", "KIV2", "KIV11", "KIV20", "KIV26", "KIV16", "KIV25", "KIV3", "KIV36", "KIV27", "KIV6", "KIV15", "KIV34", "KIV30", "KIV4", "KIV37", "KIV23", "KIV21", "KIV1", "KIV7", "KIV24", "KIV12", "KIV5", "KIV28", "KIV13", "KIV10", "KIV9", "KIV14", "KIV18", "KIV19", "KIV31", "KIV32", "KIV33", "KIV29", "KIV38", "KIV22", "KIV35"], "lib": ["NC Indigent PF sous DIU ou Implant gratuit", "Nouveaux cas TBC + d\u00c3\u00a9pist\u00c3\u00a9s (3 examens crachat)", "Nombre des visites \u00c3\u00a0\u00c2\u00a0 domicile r\u00c3\u00a9alis\u00c3\u00a9es", "Nouveau  cas suivi en observation", "Pilule + Inj (Nouv acceptantes) (si score qualit\u00c3\u00a9 >ou= \u00c3\u00a0\u00c2\u00a0 60%)", "PF Naturelle nouvelles inscrites couples autonomes", "CPN: 2\u00c3\u00a8me visite au 42e jour", "Indigent ayant re\u00c3\u00a7u Implants ou DIU", "Accouchements assist\u00c3\u00a9s avec 3 CPN (si score qualit\u00c3\u00a9 > ou = \u00c3\u00a0\u00c2\u00a0 60%)", "Patients graves r\u00c3\u00a9f\u00c3\u00a9r\u00c3\u00a9s et arriv\u00c3\u00a9 \u00c3\u00a0 l'h\u00c3\u00b4pital", "R\u00c3\u00a9union  d'analyse des donn\u00c3\u00a9es SNIS  y compris les donn\u00c3\u00a9es financi\u00c3\u00a8res  transmis  en annexe du SNIS  au BCZS  et rapport  SSR  transmis chez AAP", "Cas de VVS Refer\u00c3\u00a9s  et arriv\u00c3\u00a9es \u00c3\u00a0\u00c2\u00a0 l'Hopital", "Enfants compl\u00c3\u00a8tement vaccin\u00c3\u00a9s", "PF: Insertion d'implants ou DIU 2% par an", "Nbre des jeunes de 10 \u00c3\u00a0\u00c2\u00a0 24 ans ayant b\u00c3\u00a9n\u00c3\u00a9fici\u00c3\u00a9 le service  SSR", "Nombre d'Accouch\u00c3\u00a9es VIH+ mis sous traitement", "Enfant de 12 \u00c3\u00a0\u00c2\u00a0 59 mois inscrit \u00c3\u00a0\u00c2\u00a0la CPS 2", "R\u00c3\u00a9union  d'analyse des donn\u00c3\u00a9es SNIS  y compris les donn\u00c3\u00a9es financi\u00c3\u00a8res", "CPN 3 visites standards accomplies", "PF. Nombre des cas de Ligature et Vasectomie  r\u00c3\u00a9f\u00c3\u00a9r\u00c3\u00a9s et arriv\u00c3\u00a9 \u00c3\u00a0\u00c2\u00a0 l'h\u00c3\u00b4pital", "Consultations externes", "Femme enceinte ayant re\u00c3\u00a7u VAT 2+", "Accouchements assist\u00c3\u00a9s dans FOSA (si score qualit\u00c3\u00a9 >ou= \u00c3\u00a0\u00c2\u00a0 60%)", "Pilule + Inj (Anc acceptantes) (si score qualit\u00c3\u00a9 >ou= \u00c3\u00a0\u00c2\u00a0 60%)", "Enfant 12 \u00c3\u00a0\u00c2\u00a0 59 mois ayant r\u00c3\u00a9alis\u00c3\u00a9 4 visites standards (1/trim)", "Nombre des femmes enceintes test\u00c3\u00a9es au VIH", "NC Indigent nouvelle utilisatrice (Pillule+Injection)", "Grossesses \u00c3\u00a0\u00c2\u00a0 haut risque r\u00c3\u00a9f\u00c3\u00a9r\u00c3\u00a9e et arriv\u00c3\u00a9e", "Nombre de cas TBC trait\u00c3\u00a9s et BK- apr\u00c3\u00a8s 6 mois", "Indigent Ancienne  utilisatrice PF (Pillule -Injection)", "PF\u00c2\u00a0: Couple ayant adh\u00c3\u00a9r\u00c3\u00a9 aux m\u00c3\u00a9thodes PF modernes", "PF Naturelle nouvelles inscrites", "Nombre des nouveau-n\u00c3\u00a9s des femmes  VIH+ mis sous traitement", "Consultations externes (nvx cas de victime  des violences sexuelles trait\u00c3\u00a9s dans 72h)", "R\u00c3\u00a9unions d'\u00c3\u00a9change avec les jeunes et adolescents de 10 \u00c3\u00a0\u00c2\u00a024 ans organis\u00c3\u00a9 au CS", "Nombre des couples test\u00c3\u00a9s au VIH pour PTME ", "Promptitude, compl\u00c3\u00a9tude et correctitude \u00c3\u00a0\u00c2\u00a0 100% du SNIS transmis au BCZS", "CPN au 4\u00c3\u00a8me mois (d\u00c3\u00a9but T2)", "Nbre des jeunes de 18 \u00c3\u00a0\u00c2\u00a0 24 ans ayant  re\u00c3\u00a7u les contraceptifs modernes"]}, "lib": "Existing patient on ART"}, "ETH15": {"matching": {"distances": [29.285714285714285, 29.285714285714285, null, null, 29.285714285714285, null, 43.57142857142857, 29.285714285714285, 29.285714285714285, 28.571428571428573, null, null, 30.0, 29.285714285714285, null, 30.0, null, null, 43.57142857142857, null, 29.285714285714285, 43.57142857142857, 29.285714285714285, 43.57142857142857, null, 30.0, 29.285714285714285, null, 29.285714285714285, 43.57142857142857, null, null, 29.285714285714285, null, null, 29.285714285714285, null, 43.57142857142857, null], "indicators": ["KIV17", "KIV8", "KIV39", "KIV2", "KIV11", "KIV20", "KIV26", "KIV16", "KIV25", "KIV3", "KIV36", "KIV27", "KIV6", "KIV15", "KIV34", "KIV30", "KIV4", "KIV37", "KIV23", "KIV21", "KIV1", "KIV7", "KIV24", "KIV12", "KIV5", "KIV28", "KIV13", "KIV10", "KIV9", "KIV14", "KIV18", "KIV19", "KIV31", "KIV32", "KIV33", "KIV29", "KIV38", "KIV22", "KIV35"], "lib": ["NC Indigent PF sous DIU ou Implant gratuit", "Nouveaux cas TBC + d\u00c3\u00a9pist\u00c3\u00a9s (3 examens crachat)", "Nombre des visites \u00c3\u00a0\u00c2\u00a0 domicile r\u00c3\u00a9alis\u00c3\u00a9es", "Nouveau  cas suivi en observation", "Pilule + Inj (Nouv acceptantes) (si score qualit\u00c3\u00a9 >ou= \u00c3\u00a0\u00c2\u00a0 60%)", "PF Naturelle nouvelles inscrites couples autonomes", "CPN: 2\u00c3\u00a8me visite au 42e jour", "Indigent ayant re\u00c3\u00a7u Implants ou DIU", "Accouchements assist\u00c3\u00a9s avec 3 CPN (si score qualit\u00c3\u00a9 > ou = \u00c3\u00a0\u00c2\u00a0 60%)", "Patients graves r\u00c3\u00a9f\u00c3\u00a9r\u00c3\u00a9s et arriv\u00c3\u00a9 \u00c3\u00a0 l'h\u00c3\u00b4pital", "R\u00c3\u00a9union  d'analyse des donn\u00c3\u00a9es SNIS  y compris les donn\u00c3\u00a9es financi\u00c3\u00a8res  transmis  en annexe du SNIS  au BCZS  et rapport  SSR  transmis chez AAP", "Cas de VVS Refer\u00c3\u00a9s  et arriv\u00c3\u00a9es \u00c3\u00a0\u00c2\u00a0 l'Hopital", "Enfants compl\u00c3\u00a8tement vaccin\u00c3\u00a9s", "PF: Insertion d'implants ou DIU 2% par an", "Nbre des jeunes de 10 \u00c3\u00a0\u00c2\u00a0 24 ans ayant b\u00c3\u00a9n\u00c3\u00a9fici\u00c3\u00a9 le service  SSR", "Nombre d'Accouch\u00c3\u00a9es VIH+ mis sous traitement", "Enfant de 12 \u00c3\u00a0\u00c2\u00a0 59 mois inscrit \u00c3\u00a0\u00c2\u00a0la CPS 2", "R\u00c3\u00a9union  d'analyse des donn\u00c3\u00a9es SNIS  y compris les donn\u00c3\u00a9es financi\u00c3\u00a8res", "CPN 3 visites standards accomplies", "PF. Nombre des cas de Ligature et Vasectomie  r\u00c3\u00a9f\u00c3\u00a9r\u00c3\u00a9s et arriv\u00c3\u00a9 \u00c3\u00a0\u00c2\u00a0 l'h\u00c3\u00b4pital", "Consultations externes", "Femme enceinte ayant re\u00c3\u00a7u VAT 2+", "Accouchements assist\u00c3\u00a9s dans FOSA (si score qualit\u00c3\u00a9 >ou= \u00c3\u00a0\u00c2\u00a0 60%)", "Pilule + Inj (Anc acceptantes) (si score qualit\u00c3\u00a9 >ou= \u00c3\u00a0\u00c2\u00a0 60%)", "Enfant 12 \u00c3\u00a0\u00c2\u00a0 59 mois ayant r\u00c3\u00a9alis\u00c3\u00a9 4 visites standards (1/trim)", "Nombre des femmes enceintes test\u00c3\u00a9es au VIH", "NC Indigent nouvelle utilisatrice (Pillule+Injection)", "Grossesses \u00c3\u00a0\u00c2\u00a0 haut risque r\u00c3\u00a9f\u00c3\u00a9r\u00c3\u00a9e et arriv\u00c3\u00a9e", "Nombre de cas TBC trait\u00c3\u00a9s et BK- apr\u00c3\u00a8s 6 mois", "Indigent Ancienne  utilisatrice PF (Pillule -Injection)", "PF\u00c2\u00a0: Couple ayant adh\u00c3\u00a9r\u00c3\u00a9 aux m\u00c3\u00a9thodes PF modernes", "PF Naturelle nouvelles inscrites", "Nombre des nouveau-n\u00c3\u00a9s des femmes  VIH+ mis sous traitement", "Consultations externes (nvx cas de victime  des violences sexuelles trait\u00c3\u00a9s dans 72h)", "R\u00c3\u00a9unions d'\u00c3\u00a9change avec les jeunes et adolescents de 10 \u00c3\u00a0\u00c2\u00a024 ans organis\u00c3\u00a9 au CS", "Nombre des couples test\u00c3\u00a9s au VIH pour PTME ", "Promptitude, compl\u00c3\u00a9tude et correctitude \u00c3\u00a0\u00c2\u00a0 100% du SNIS transmis au BCZS", "CPN au 4\u00c3\u00a8me mois (d\u00c3\u00a9but T2)", "Nbre des jeunes de 18 \u00c3\u00a0\u00c2\u00a0 24 ans ayant  re\u00c3\u00a7u les contraceptifs modernes"]}, "lib": "Referred deliveries received from health center"}, "ETH9": {"matching": {"distances": [23.88888888888889, 24.444444444444443, null, null, 23.88888888888889, null, 34.44444444444444, 23.88888888888889, 23.88888888888889, 24.444444444444443, null, null, 25.555555555555557, 23.88888888888889, null, 12.222222222222221, null, null, 34.44444444444444, null, 24.444444444444443, 34.44444444444444, 23.333333333333332, 35.0, null, 12.222222222222221, 23.88888888888889, null, 23.88888888888889, 35.0, null, null, 12.777777777777779, null, null, 13.333333333333334, null, 34.44444444444444, null], "indicators": ["KIV17", "KIV8", "KIV39", "KIV2", "KIV11", "KIV20", "KIV26", "KIV16", "KIV25", "KIV3", "KIV36", "KIV27", "KIV6", "KIV15", "KIV34", "KIV30", "KIV4", "KIV37", "KIV23", "KIV21", "KIV1", "KIV7", "KIV24", "KIV12", "KIV5", "KIV28", "KIV13", "KIV10", "KIV9", "KIV14", "KIV18", "KIV19", "KIV31", "KIV32", "KIV33", "KIV29", "KIV38", "KIV22", "KIV35"], "lib": ["NC Indigent PF sous DIU ou Implant gratuit", "Nouveaux cas TBC + d\u00c3\u00a9pist\u00c3\u00a9s (3 examens crachat)", "Nombre des visites \u00c3\u00a0\u00c2\u00a0 domicile r\u00c3\u00a9alis\u00c3\u00a9es", "Nouveau  cas suivi en observation", "Pilule + Inj (Nouv acceptantes) (si score qualit\u00c3\u00a9 >ou= \u00c3\u00a0\u00c2\u00a0 60%)", "PF Naturelle nouvelles inscrites couples autonomes", "CPN: 2\u00c3\u00a8me visite au 42e jour", "Indigent ayant re\u00c3\u00a7u Implants ou DIU", "Accouchements assist\u00c3\u00a9s avec 3 CPN (si score qualit\u00c3\u00a9 > ou = \u00c3\u00a0\u00c2\u00a0 60%)", "Patients graves r\u00c3\u00a9f\u00c3\u00a9r\u00c3\u00a9s et arriv\u00c3\u00a9 \u00c3\u00a0 l'h\u00c3\u00b4pital", "R\u00c3\u00a9union  d'analyse des donn\u00c3\u00a9es SNIS  y compris les donn\u00c3\u00a9es financi\u00c3\u00a8res  transmis  en annexe du SNIS  au BCZS  et rapport  SSR  transmis chez AAP", "Cas de VVS Refer\u00c3\u00a9s  et arriv\u00c3\u00a9es \u00c3\u00a0\u00c2\u00a0 l'Hopital", "Enfants compl\u00c3\u00a8tement vaccin\u00c3\u00a9s", "PF: Insertion d'implants ou DIU 2% par an", "Nbre des jeunes de 10 \u00c3\u00a0\u00c2\u00a0 24 ans ayant b\u00c3\u00a9n\u00c3\u00a9fici\u00c3\u00a9 le service  SSR", "Nombre d'Accouch\u00c3\u00a9es VIH+ mis sous traitement", "Enfant de 12 \u00c3\u00a0\u00c2\u00a0 59 mois inscrit \u00c3\u00a0\u00c2\u00a0la CPS 2", "R\u00c3\u00a9union  d'analyse des donn\u00c3\u00a9es SNIS  y compris les donn\u00c3\u00a9es financi\u00c3\u00a8res", "CPN 3 visites standards accomplies", "PF. Nombre des cas de Ligature et Vasectomie  r\u00c3\u00a9f\u00c3\u00a9r\u00c3\u00a9s et arriv\u00c3\u00a9 \u00c3\u00a0\u00c2\u00a0 l'h\u00c3\u00b4pital", "Consultations externes", "Femme enceinte ayant re\u00c3\u00a7u VAT 2+", "Accouchements assist\u00c3\u00a9s dans FOSA (si score qualit\u00c3\u00a9 >ou= \u00c3\u00a0\u00c2\u00a0 60%)", "Pilule + Inj (Anc acceptantes) (si score qualit\u00c3\u00a9 >ou= \u00c3\u00a0\u00c2\u00a0 60%)", "Enfant 12 \u00c3\u00a0\u00c2\u00a0 59 mois ayant r\u00c3\u00a9alis\u00c3\u00a9 4 visites standards (1/trim)", "Nombre des femmes enceintes test\u00c3\u00a9es au VIH", "NC Indigent nouvelle utilisatrice (Pillule+Injection)", "Grossesses \u00c3\u00a0\u00c2\u00a0 haut risque r\u00c3\u00a9f\u00c3\u00a9r\u00c3\u00a9e et arriv\u00c3\u00a9e", "Nombre de cas TBC trait\u00c3\u00a9s et BK- apr\u00c3\u00a8s 6 mois", "Indigent Ancienne  utilisatrice PF (Pillule -Injection)", "PF\u00c2\u00a0: Couple ayant adh\u00c3\u00a9r\u00c3\u00a9 aux m\u00c3\u00a9thodes PF modernes", "PF Naturelle nouvelles inscrites", "Nombre des nouveau-n\u00c3\u00a9s des femmes  VIH+ mis sous traitement", "Consultations externes (nvx cas de victime  des violences sexuelles trait\u00c3\u00a9s dans 72h)", "R\u00c3\u00a9unions d'\u00c3\u00a9change avec les jeunes et adolescents de 10 \u00c3\u00a0\u00c2\u00a024 ans organis\u00c3\u00a9 au CS", "Nombre des couples test\u00c3\u00a9s au VIH pour PTME ", "Promptitude, compl\u00c3\u00a9tude et correctitude \u00c3\u00a0\u00c2\u00a0 100% du SNIS transmis au BCZS", "CPN au 4\u00c3\u00a8me mois (d\u00c3\u00a9but T2)", "Nbre des jeunes de 18 \u00c3\u00a0\u00c2\u00a0 24 ans ayant  re\u00c3\u00a7u les contraceptifs modernes"]}, "lib": "HIV positive tested pregnant women put on PMTCT option B+"}, "ETH3": {"matching": {"distances": [38.75, 38.125, null, null, 38.125, null, 38.75, 38.75, 38.75, 38.125, null, null, 38.75, 38.125, null, 39.375, null, null, 38.75, null, 38.125, 38.75, 38.75, 38.125, null, 39.375, 38.75, null, 38.125, 38.75, null, null, 38.75, null, null, 38.75, null, 38.75, null], "indicators": ["KIV17", "KIV8", "KIV39", "KIV2", "KIV11", "KIV20", "KIV26", "KIV16", "KIV25", "KIV3", "KIV36", "KIV27", "KIV6", "KIV15", "KIV34", "KIV30", "KIV4", "KIV37", "KIV23", "KIV21", "KIV1", "KIV7", "KIV24", "KIV12", "KIV5", "KIV28", "KIV13", "KIV10", "KIV9", "KIV14", "KIV18", "KIV19", "KIV31", "KIV32", "KIV33", "KIV29", "KIV38", "KIV22", "KIV35"], "lib": ["NC Indigent PF sous DIU ou Implant gratuit", "Nouveaux cas TBC + d\u00c3\u00a9pist\u00c3\u00a9s (3 examens crachat)", "Nombre des visites \u00c3\u00a0\u00c2\u00a0 domicile r\u00c3\u00a9alis\u00c3\u00a9es", "Nouveau  cas suivi en observation", "Pilule + Inj (Nouv acceptantes) (si score qualit\u00c3\u00a9 >ou= \u00c3\u00a0\u00c2\u00a0 60%)", "PF Naturelle nouvelles inscrites couples autonomes", "CPN: 2\u00c3\u00a8me visite au 42e jour", "Indigent ayant re\u00c3\u00a7u Implants ou DIU", "Accouchements assist\u00c3\u00a9s avec 3 CPN (si score qualit\u00c3\u00a9 > ou = \u00c3\u00a0\u00c2\u00a0 60%)", "Patients graves r\u00c3\u00a9f\u00c3\u00a9r\u00c3\u00a9s et arriv\u00c3\u00a9 \u00c3\u00a0 l'h\u00c3\u00b4pital", "R\u00c3\u00a9union  d'analyse des donn\u00c3\u00a9es SNIS  y compris les donn\u00c3\u00a9es financi\u00c3\u00a8res  transmis  en annexe du SNIS  au BCZS  et rapport  SSR  transmis chez AAP", "Cas de VVS Refer\u00c3\u00a9s  et arriv\u00c3\u00a9es \u00c3\u00a0\u00c2\u00a0 l'Hopital", "Enfants compl\u00c3\u00a8tement vaccin\u00c3\u00a9s", "PF: Insertion d'implants ou DIU 2% par an", "Nbre des jeunes de 10 \u00c3\u00a0\u00c2\u00a0 24 ans ayant b\u00c3\u00a9n\u00c3\u00a9fici\u00c3\u00a9 le service  SSR", "Nombre d'Accouch\u00c3\u00a9es VIH+ mis sous traitement", "Enfant de 12 \u00c3\u00a0\u00c2\u00a0 59 mois inscrit \u00c3\u00a0\u00c2\u00a0la CPS 2", "R\u00c3\u00a9union  d'analyse des donn\u00c3\u00a9es SNIS  y compris les donn\u00c3\u00a9es financi\u00c3\u00a8res", "CPN 3 visites standards accomplies", "PF. Nombre des cas de Ligature et Vasectomie  r\u00c3\u00a9f\u00c3\u00a9r\u00c3\u00a9s et arriv\u00c3\u00a9 \u00c3\u00a0\u00c2\u00a0 l'h\u00c3\u00b4pital", "Consultations externes", "Femme enceinte ayant re\u00c3\u00a7u VAT 2+", "Accouchements assist\u00c3\u00a9s dans FOSA (si score qualit\u00c3\u00a9 >ou= \u00c3\u00a0\u00c2\u00a0 60%)", "Pilule + Inj (Anc acceptantes) (si score qualit\u00c3\u00a9 >ou= \u00c3\u00a0\u00c2\u00a0 60%)", "Enfant 12 \u00c3\u00a0\u00c2\u00a0 59 mois ayant r\u00c3\u00a9alis\u00c3\u00a9 4 visites standards (1/trim)", "Nombre des femmes enceintes test\u00c3\u00a9es au VIH", "NC Indigent nouvelle utilisatrice (Pillule+Injection)", "Grossesses \u00c3\u00a0\u00c2\u00a0 haut risque r\u00c3\u00a9f\u00c3\u00a9r\u00c3\u00a9e et arriv\u00c3\u00a9e", "Nombre de cas TBC trait\u00c3\u00a9s et BK- apr\u00c3\u00a8s 6 mois", "Indigent Ancienne  utilisatrice PF (Pillule -Injection)", "PF\u00c2\u00a0: Couple ayant adh\u00c3\u00a9r\u00c3\u00a9 aux m\u00c3\u00a9thodes PF modernes", "PF Naturelle nouvelles inscrites", "Nombre des nouveau-n\u00c3\u00a9s des femmes  VIH+ mis sous traitement", "Consultations externes (nvx cas de victime  des violences sexuelles trait\u00c3\u00a9s dans 72h)", "R\u00c3\u00a9unions d'\u00c3\u00a9change avec les jeunes et adolescents de 10 \u00c3\u00a0\u00c2\u00a024 ans organis\u00c3\u00a9 au CS", "Nombre des couples test\u00c3\u00a9s au VIH pour PTME ", "Promptitude, compl\u00c3\u00a9tude et correctitude \u00c3\u00a0\u00c2\u00a0 100% du SNIS transmis au BCZS", "CPN au 4\u00c3\u00a8me mois (d\u00c3\u00a9but T2)", "Nbre des jeunes de 18 \u00c3\u00a0\u00c2\u00a0 24 ans ayant  re\u00c3\u00a7u les contraceptifs modernes"]}, "lib": "Hospital bed days (observation/hospitalization)"}, "ETH5": {"matching": {"distances": [23.88888888888889, 23.333333333333332, null, null, 23.333333333333332, null, 35.0, 23.88888888888889, 23.88888888888889, 23.333333333333332, null, null, 23.88888888888889, 23.333333333333332, null, 24.444444444444443, null, null, 35.0, null, 23.333333333333332, 35.0, 23.88888888888889, 34.44444444444444, null, 24.444444444444443, 23.88888888888889, null, 23.333333333333332, 35.0, null, null, 23.88888888888889, null, null, 23.88888888888889, null, 35.0, null], "indicators": ["KIV17", "KIV8", "KIV39", "KIV2", "KIV11", "KIV20", "KIV26", "KIV16", "KIV25", "KIV3", "KIV36", "KIV27", "KIV6", "KIV15", "KIV34", "KIV30", "KIV4", "KIV37", "KIV23", "KIV21", "KIV1", "KIV7", "KIV24", "KIV12", "KIV5", "KIV28", "KIV13", "KIV10", "KIV9", "KIV14", "KIV18", "KIV19", "KIV31", "KIV32", "KIV33", "KIV29", "KIV38", "KIV22", "KIV35"], "lib": ["NC Indigent PF sous DIU ou Implant gratuit", "Nouveaux cas TBC + d\u00c3\u00a9pist\u00c3\u00a9s (3 examens crachat)", "Nombre des visites \u00c3\u00a0\u00c2\u00a0 domicile r\u00c3\u00a9alis\u00c3\u00a9es", "Nouveau  cas suivi en observation", "Pilule + Inj (Nouv acceptantes) (si score qualit\u00c3\u00a9 >ou= \u00c3\u00a0\u00c2\u00a0 60%)", "PF Naturelle nouvelles inscrites couples autonomes", "CPN: 2\u00c3\u00a8me visite au 42e jour", "Indigent ayant re\u00c3\u00a7u Implants ou DIU", "Accouchements assist\u00c3\u00a9s avec 3 CPN (si score qualit\u00c3\u00a9 > ou = \u00c3\u00a0\u00c2\u00a0 60%)", "Patients graves r\u00c3\u00a9f\u00c3\u00a9r\u00c3\u00a9s et arriv\u00c3\u00a9 \u00c3\u00a0 l'h\u00c3\u00b4pital", "R\u00c3\u00a9union  d'analyse des donn\u00c3\u00a9es SNIS  y compris les donn\u00c3\u00a9es financi\u00c3\u00a8res  transmis  en annexe du SNIS  au BCZS  et rapport  SSR  transmis chez AAP", "Cas de VVS Refer\u00c3\u00a9s  et arriv\u00c3\u00a9es \u00c3\u00a0\u00c2\u00a0 l'Hopital", "Enfants compl\u00c3\u00a8tement vaccin\u00c3\u00a9s", "PF: Insertion d'implants ou DIU 2% par an", "Nbre des jeunes de 10 \u00c3\u00a0\u00c2\u00a0 24 ans ayant b\u00c3\u00a9n\u00c3\u00a9fici\u00c3\u00a9 le service  SSR", "Nombre d'Accouch\u00c3\u00a9es VIH+ mis sous traitement", "Enfant de 12 \u00c3\u00a0\u00c2\u00a0 59 mois inscrit \u00c3\u00a0\u00c2\u00a0la CPS 2", "R\u00c3\u00a9union  d'analyse des donn\u00c3\u00a9es SNIS  y compris les donn\u00c3\u00a9es financi\u00c3\u00a8res", "CPN 3 visites standards accomplies", "PF. Nombre des cas de Ligature et Vasectomie  r\u00c3\u00a9f\u00c3\u00a9r\u00c3\u00a9s et arriv\u00c3\u00a9 \u00c3\u00a0\u00c2\u00a0 l'h\u00c3\u00b4pital", "Consultations externes", "Femme enceinte ayant re\u00c3\u00a7u VAT 2+", "Accouchements assist\u00c3\u00a9s dans FOSA (si score qualit\u00c3\u00a9 >ou= \u00c3\u00a0\u00c2\u00a0 60%)", "Pilule + Inj (Anc acceptantes) (si score qualit\u00c3\u00a9 >ou= \u00c3\u00a0\u00c2\u00a0 60%)", "Enfant 12 \u00c3\u00a0\u00c2\u00a0 59 mois ayant r\u00c3\u00a9alis\u00c3\u00a9 4 visites standards (1/trim)", "Nombre des femmes enceintes test\u00c3\u00a9es au VIH", "NC Indigent nouvelle utilisatrice (Pillule+Injection)", "Grossesses \u00c3\u00a0\u00c2\u00a0 haut risque r\u00c3\u00a9f\u00c3\u00a9r\u00c3\u00a9e et arriv\u00c3\u00a9e", "Nombre de cas TBC trait\u00c3\u00a9s et BK- apr\u00c3\u00a8s 6 mois", "Indigent Ancienne  utilisatrice PF (Pillule -Injection)", "PF\u00c2\u00a0: Couple ayant adh\u00c3\u00a9r\u00c3\u00a9 aux m\u00c3\u00a9thodes PF modernes", "PF Naturelle nouvelles inscrites", "Nombre des nouveau-n\u00c3\u00a9s des femmes  VIH+ mis sous traitement", "Consultations externes (nvx cas de victime  des violences sexuelles trait\u00c3\u00a9s dans 72h)", "R\u00c3\u00a9unions d'\u00c3\u00a9change avec les jeunes et adolescents de 10 \u00c3\u00a0\u00c2\u00a024 ans organis\u00c3\u00a9 au CS", "Nombre des couples test\u00c3\u00a9s au VIH pour PTME ", "Promptitude, compl\u00c3\u00a9tude et correctitude \u00c3\u00a0\u00c2\u00a0 100% du SNIS transmis au BCZS", "CPN au 4\u00c3\u00a8me mois (d\u00c3\u00a9but T2)", "Nbre des jeunes de 18 \u00c3\u00a0\u00c2\u00a0 24 ans ayant  re\u00c3\u00a7u les contraceptifs modernes"]}, "lib": "Minor surgery cases"}, "ETH14": {"matching": {"distances": [24.444444444444443, 12.222222222222221, null, null, 23.88888888888889, null, 35.55555555555556, 24.444444444444443, 24.444444444444443, 23.88888888888889, null, null, 24.444444444444443, 23.88888888888889, null, 23.88888888888889, null, null, 35.55555555555556, null, 23.333333333333332, 35.55555555555556, 24.444444444444443, 35.0, null, 24.444444444444443, 24.444444444444443, null, 11.666666666666666, 35.55555555555556, null, null, 23.333333333333332, null, null, 23.88888888888889, null, 35.55555555555556, null], "indicators": ["KIV17", "KIV8", "KIV39", "KIV2", "KIV11", "KIV20", "KIV26", "KIV16", "KIV25", "KIV3", "KIV36", "KIV27", "KIV6", "KIV15", "KIV34", "KIV30", "KIV4", "KIV37", "KIV23", "KIV21", "KIV1", "KIV7", "KIV24", "KIV12", "KIV5", "KIV28", "KIV13", "KIV10", "KIV9", "KIV14", "KIV18", "KIV19", "KIV31", "KIV32", "KIV33", "KIV29", "KIV38", "KIV22", "KIV35"], "lib": ["NC Indigent PF sous DIU ou Implant gratuit", "Nouveaux cas TBC + d\u00c3\u00a9pist\u00c3\u00a9s (3 examens crachat)", "Nombre des visites \u00c3\u00a0\u00c2\u00a0 domicile r\u00c3\u00a9alis\u00c3\u00a9es", "Nouveau  cas suivi en observation", "Pilule + Inj (Nouv acceptantes) (si score qualit\u00c3\u00a9 >ou= \u00c3\u00a0\u00c2\u00a0 60%)", "PF Naturelle nouvelles inscrites couples autonomes", "CPN: 2\u00c3\u00a8me visite au 42e jour", "Indigent ayant re\u00c3\u00a7u Implants ou DIU", "Accouchements assist\u00c3\u00a9s avec 3 CPN (si score qualit\u00c3\u00a9 > ou = \u00c3\u00a0\u00c2\u00a0 60%)", "Patients graves r\u00c3\u00a9f\u00c3\u00a9r\u00c3\u00a9s et arriv\u00c3\u00a9 \u00c3\u00a0 l'h\u00c3\u00b4pital", "R\u00c3\u00a9union  d'analyse des donn\u00c3\u00a9es SNIS  y compris les donn\u00c3\u00a9es financi\u00c3\u00a8res  transmis  en annexe du SNIS  au BCZS  et rapport  SSR  transmis chez AAP", "Cas de VVS Refer\u00c3\u00a9s  et arriv\u00c3\u00a9es \u00c3\u00a0\u00c2\u00a0 l'Hopital", "Enfants compl\u00c3\u00a8tement vaccin\u00c3\u00a9s", "PF: Insertion d'implants ou DIU 2% par an", "Nbre des jeunes de 10 \u00c3\u00a0\u00c2\u00a0 24 ans ayant b\u00c3\u00a9n\u00c3\u00a9fici\u00c3\u00a9 le service  SSR", "Nombre d'Accouch\u00c3\u00a9es VIH+ mis sous traitement", "Enfant de 12 \u00c3\u00a0\u00c2\u00a0 59 mois inscrit \u00c3\u00a0\u00c2\u00a0la CPS 2", "R\u00c3\u00a9union  d'analyse des donn\u00c3\u00a9es SNIS  y compris les donn\u00c3\u00a9es financi\u00c3\u00a8res", "CPN 3 visites standards accomplies", "PF. Nombre des cas de Ligature et Vasectomie  r\u00c3\u00a9f\u00c3\u00a9r\u00c3\u00a9s et arriv\u00c3\u00a9 \u00c3\u00a0\u00c2\u00a0 l'h\u00c3\u00b4pital", "Consultations externes", "Femme enceinte ayant re\u00c3\u00a7u VAT 2+", "Accouchements assist\u00c3\u00a9s dans FOSA (si score qualit\u00c3\u00a9 >ou= \u00c3\u00a0\u00c2\u00a0 60%)", "Pilule + Inj (Anc acceptantes) (si score qualit\u00c3\u00a9 >ou= \u00c3\u00a0\u00c2\u00a0 60%)", "Enfant 12 \u00c3\u00a0\u00c2\u00a0 59 mois ayant r\u00c3\u00a9alis\u00c3\u00a9 4 visites standards (1/trim)", "Nombre des femmes enceintes test\u00c3\u00a9es au VIH", "NC Indigent nouvelle utilisatrice (Pillule+Injection)", "Grossesses \u00c3\u00a0\u00c2\u00a0 haut risque r\u00c3\u00a9f\u00c3\u00a9r\u00c3\u00a9e et arriv\u00c3\u00a9e", "Nombre de cas TBC trait\u00c3\u00a9s et BK- apr\u00c3\u00a8s 6 mois", "Indigent Ancienne  utilisatrice PF (Pillule -Injection)", "PF\u00c2\u00a0: Couple ayant adh\u00c3\u00a9r\u00c3\u00a9 aux m\u00c3\u00a9thodes PF modernes", "PF Naturelle nouvelles inscrites", "Nombre des nouveau-n\u00c3\u00a9s des femmes  VIH+ mis sous traitement", "Consultations externes (nvx cas de victime  des violences sexuelles trait\u00c3\u00a9s dans 72h)", "R\u00c3\u00a9unions d'\u00c3\u00a9change avec les jeunes et adolescents de 10 \u00c3\u00a0\u00c2\u00a024 ans organis\u00c3\u00a9 au CS", "Nombre des couples test\u00c3\u00a9s au VIH pour PTME ", "Promptitude, compl\u00c3\u00a9tude et correctitude \u00c3\u00a0\u00c2\u00a0 100% du SNIS transmis au BCZS", "CPN au 4\u00c3\u00a8me mois (d\u00c3\u00a9but T2)", "Nbre des jeunes de 18 \u00c3\u00a0\u00c2\u00a0 24 ans ayant  re\u00c3\u00a7u les contraceptifs modernes"]}, "lib": "Cases of TB treated and cured"}, "ETH1": {"matching": {"distances": [24.444444444444443, 23.333333333333332, null, null, 23.88888888888889, null, 35.55555555555556, 24.444444444444443, 24.444444444444443, 12.777777777777779, null, null, 24.444444444444443, 23.88888888888889, null, 24.444444444444443, null, null, 35.55555555555556, null, 11.11111111111111, 35.55555555555556, 24.444444444444443, 35.0, null, 24.444444444444443, 24.444444444444443, null, 23.333333333333332, 35.55555555555556, null, null, 23.88888888888889, null, null, 23.88888888888889, null, 35.55555555555556, null], "indicators": ["KIV17", "KIV8", "KIV39", "KIV2", "KIV11", "KIV20", "KIV26", "KIV16", "KIV25", "KIV3", "KIV36", "KIV27", "KIV6", "KIV15", "KIV34", "KIV30", "KIV4", "KIV37", "KIV23", "KIV21", "KIV1", "KIV7", "KIV24", "KIV12", "KIV5", "KIV28", "KIV13", "KIV10", "KIV9", "KIV14", "KIV18", "KIV19", "KIV31", "KIV32", "KIV33", "KIV29", "KIV38", "KIV22", "KIV35"], "lib": ["NC Indigent PF sous DIU ou Implant gratuit", "Nouveaux cas TBC + d\u00c3\u00a9pist\u00c3\u00a9s (3 examens crachat)", "Nombre des visites \u00c3\u00a0\u00c2\u00a0 domicile r\u00c3\u00a9alis\u00c3\u00a9es", "Nouveau  cas suivi en observation", "Pilule + Inj (Nouv acceptantes) (si score qualit\u00c3\u00a9 >ou= \u00c3\u00a0\u00c2\u00a0 60%)", "PF Naturelle nouvelles inscrites couples autonomes", "CPN: 2\u00c3\u00a8me visite au 42e jour", "Indigent ayant re\u00c3\u00a7u Implants ou DIU", "Accouchements assist\u00c3\u00a9s avec 3 CPN (si score qualit\u00c3\u00a9 > ou = \u00c3\u00a0\u00c2\u00a0 60%)", "Patients graves r\u00c3\u00a9f\u00c3\u00a9r\u00c3\u00a9s et arriv\u00c3\u00a9 \u00c3\u00a0 l'h\u00c3\u00b4pital", "R\u00c3\u00a9union  d'analyse des donn\u00c3\u00a9es SNIS  y compris les donn\u00c3\u00a9es financi\u00c3\u00a8res  transmis  en annexe du SNIS  au BCZS  et rapport  SSR  transmis chez AAP", "Cas de VVS Refer\u00c3\u00a9s  et arriv\u00c3\u00a9es \u00c3\u00a0\u00c2\u00a0 l'Hopital", "Enfants compl\u00c3\u00a8tement vaccin\u00c3\u00a9s", "PF: Insertion d'implants ou DIU 2% par an", "Nbre des jeunes de 10 \u00c3\u00a0\u00c2\u00a0 24 ans ayant b\u00c3\u00a9n\u00c3\u00a9fici\u00c3\u00a9 le service  SSR", "Nombre d'Accouch\u00c3\u00a9es VIH+ mis sous traitement", "Enfant de 12 \u00c3\u00a0\u00c2\u00a0 59 mois inscrit \u00c3\u00a0\u00c2\u00a0la CPS 2", "R\u00c3\u00a9union  d'analyse des donn\u00c3\u00a9es SNIS  y compris les donn\u00c3\u00a9es financi\u00c3\u00a8res", "CPN 3 visites standards accomplies", "PF. Nombre des cas de Ligature et Vasectomie  r\u00c3\u00a9f\u00c3\u00a9r\u00c3\u00a9s et arriv\u00c3\u00a9 \u00c3\u00a0\u00c2\u00a0 l'h\u00c3\u00b4pital", "Consultations externes", "Femme enceinte ayant re\u00c3\u00a7u VAT 2+", "Accouchements assist\u00c3\u00a9s dans FOSA (si score qualit\u00c3\u00a9 >ou= \u00c3\u00a0\u00c2\u00a0 60%)", "Pilule + Inj (Anc acceptantes) (si score qualit\u00c3\u00a9 >ou= \u00c3\u00a0\u00c2\u00a0 60%)", "Enfant 12 \u00c3\u00a0\u00c2\u00a0 59 mois ayant r\u00c3\u00a9alis\u00c3\u00a9 4 visites standards (1/trim)", "Nombre des femmes enceintes test\u00c3\u00a9es au VIH", "NC Indigent nouvelle utilisatrice (Pillule+Injection)", "Grossesses \u00c3\u00a0\u00c2\u00a0 haut risque r\u00c3\u00a9f\u00c3\u00a9r\u00c3\u00a9e et arriv\u00c3\u00a9e", "Nombre de cas TBC trait\u00c3\u00a9s et BK- apr\u00c3\u00a8s 6 mois", "Indigent Ancienne  utilisatrice PF (Pillule -Injection)", "PF\u00c2\u00a0: Couple ayant adh\u00c3\u00a9r\u00c3\u00a9 aux m\u00c3\u00a9thodes PF modernes", "PF Naturelle nouvelles inscrites", "Nombre des nouveau-n\u00c3\u00a9s des femmes  VIH+ mis sous traitement", "Consultations externes (nvx cas de victime  des violences sexuelles trait\u00c3\u00a9s dans 72h)", "R\u00c3\u00a9unions d'\u00c3\u00a9change avec les jeunes et adolescents de 10 \u00c3\u00a0\u00c2\u00a024 ans organis\u00c3\u00a9 au CS", "Nombre des couples test\u00c3\u00a9s au VIH pour PTME ", "Promptitude, compl\u00c3\u00a9tude et correctitude \u00c3\u00a0\u00c2\u00a0 100% du SNIS transmis au BCZS", "CPN au 4\u00c3\u00a8me mois (d\u00c3\u00a9but T2)", "Nbre des jeunes de 18 \u00c3\u00a0\u00c2\u00a0 24 ans ayant  re\u00c3\u00a7u les contraceptifs modernes"]}, "lib": "Out Patient Consultations (new cases)"}, "ETH13": {"matching": {"distances": [24.444444444444443, 11.11111111111111, null, null, 23.88888888888889, null, 35.55555555555556, 24.444444444444443, 24.444444444444443, 23.88888888888889, null, null, 24.444444444444443, 23.88888888888889, null, 24.444444444444443, null, null, 35.55555555555556, null, 23.333333333333332, 35.55555555555556, 24.444444444444443, 35.0, null, 24.444444444444443, 24.444444444444443, null, 12.222222222222221, 35.55555555555556, null, null, 23.88888888888889, null, null, 23.88888888888889, null, 35.55555555555556, null], "indicators": ["KIV17", "KIV8", "KIV39", "KIV2", "KIV11", "KIV20", "KIV26", "KIV16", "KIV25", "KIV3", "KIV36", "KIV27", "KIV6", "KIV15", "KIV34", "KIV30", "KIV4", "KIV37", "KIV23", "KIV21", "KIV1", "KIV7", "KIV24", "KIV12", "KIV5", "KIV28", "KIV13", "KIV10", "KIV9", "KIV14", "KIV18", "KIV19", "KIV31", "KIV32", "KIV33", "KIV29", "KIV38", "KIV22", "KIV35"], "lib": ["NC Indigent PF sous DIU ou Implant gratuit", "Nouveaux cas TBC + d\u00c3\u00a9pist\u00c3\u00a9s (3 examens crachat)", "Nombre des visites \u00c3\u00a0\u00c2\u00a0 domicile r\u00c3\u00a9alis\u00c3\u00a9es", "Nouveau  cas suivi en observation", "Pilule + Inj (Nouv acceptantes) (si score qualit\u00c3\u00a9 >ou= \u00c3\u00a0\u00c2\u00a0 60%)", "PF Naturelle nouvelles inscrites couples autonomes", "CPN: 2\u00c3\u00a8me visite au 42e jour", "Indigent ayant re\u00c3\u00a7u Implants ou DIU", "Accouchements assist\u00c3\u00a9s avec 3 CPN (si score qualit\u00c3\u00a9 > ou = \u00c3\u00a0\u00c2\u00a0 60%)", "Patients graves r\u00c3\u00a9f\u00c3\u00a9r\u00c3\u00a9s et arriv\u00c3\u00a9 \u00c3\u00a0 l'h\u00c3\u00b4pital", "R\u00c3\u00a9union  d'analyse des donn\u00c3\u00a9es SNIS  y compris les donn\u00c3\u00a9es financi\u00c3\u00a8res  transmis  en annexe du SNIS  au BCZS  et rapport  SSR  transmis chez AAP", "Cas de VVS Refer\u00c3\u00a9s  et arriv\u00c3\u00a9es \u00c3\u00a0\u00c2\u00a0 l'Hopital", "Enfants compl\u00c3\u00a8tement vaccin\u00c3\u00a9s", "PF: Insertion d'implants ou DIU 2% par an", "Nbre des jeunes de 10 \u00c3\u00a0\u00c2\u00a0 24 ans ayant b\u00c3\u00a9n\u00c3\u00a9fici\u00c3\u00a9 le service  SSR", "Nombre d'Accouch\u00c3\u00a9es VIH+ mis sous traitement", "Enfant de 12 \u00c3\u00a0\u00c2\u00a0 59 mois inscrit \u00c3\u00a0\u00c2\u00a0la CPS 2", "R\u00c3\u00a9union  d'analyse des donn\u00c3\u00a9es SNIS  y compris les donn\u00c3\u00a9es financi\u00c3\u00a8res", "CPN 3 visites standards accomplies", "PF. Nombre des cas de Ligature et Vasectomie  r\u00c3\u00a9f\u00c3\u00a9r\u00c3\u00a9s et arriv\u00c3\u00a9 \u00c3\u00a0\u00c2\u00a0 l'h\u00c3\u00b4pital", "Consultations externes", "Femme enceinte ayant re\u00c3\u00a7u VAT 2+", "Accouchements assist\u00c3\u00a9s dans FOSA (si score qualit\u00c3\u00a9 >ou= \u00c3\u00a0\u00c2\u00a0 60%)", "Pilule + Inj (Anc acceptantes) (si score qualit\u00c3\u00a9 >ou= \u00c3\u00a0\u00c2\u00a0 60%)", "Enfant 12 \u00c3\u00a0\u00c2\u00a0 59 mois ayant r\u00c3\u00a9alis\u00c3\u00a9 4 visites standards (1/trim)", "Nombre des femmes enceintes test\u00c3\u00a9es au VIH", "NC Indigent nouvelle utilisatrice (Pillule+Injection)", "Grossesses \u00c3\u00a0\u00c2\u00a0 haut risque r\u00c3\u00a9f\u00c3\u00a9r\u00c3\u00a9e et arriv\u00c3\u00a9e", "Nombre de cas TBC trait\u00c3\u00a9s et BK- apr\u00c3\u00a8s 6 mois", "Indigent Ancienne  utilisatrice PF (Pillule -Injection)", "PF\u00c2\u00a0: Couple ayant adh\u00c3\u00a9r\u00c3\u00a9 aux m\u00c3\u00a9thodes PF modernes", "PF Naturelle nouvelles inscrites", "Nombre des nouveau-n\u00c3\u00a9s des femmes  VIH+ mis sous traitement", "Consultations externes (nvx cas de victime  des violences sexuelles trait\u00c3\u00a9s dans 72h)", "R\u00c3\u00a9unions d'\u00c3\u00a9change avec les jeunes et adolescents de 10 \u00c3\u00a0\u00c2\u00a024 ans organis\u00c3\u00a9 au CS", "Nombre des couples test\u00c3\u00a9s au VIH pour PTME ", "Promptitude, compl\u00c3\u00a9tude et correctitude \u00c3\u00a0\u00c2\u00a0 100% du SNIS transmis au BCZS", "CPN au 4\u00c3\u00a8me mois (d\u00c3\u00a9but T2)", "Nbre des jeunes de 18 \u00c3\u00a0\u00c2\u00a0 24 ans ayant  re\u00c3\u00a7u les contraceptifs modernes"]}, "lib": "Cases of TB diagnosed positive by Microscopy"}, "ETH6": {"matching": {"distances": [100.0, 100.0, 100.0, 100.0, 100.0, 100.0, 100.0, 100.0, 100.0, 100.0, 100.0, 100.0, 100.0, 100.0, 100.0, 100.0, 100.0, 100.0, 100.0, 100.0, 100.0, 100.0, 100.0, 100.0, 100.0, 100.0, 100.0, 100.0, 100.0, 100.0, 100.0, 100.0, 100.0, 100.0, 100.0, 100.0, 100.0, 100.0, 100.0], "indicators": ["KIV17", "KIV8", "KIV39", "KIV2", "KIV11", "KIV20", "KIV26", "KIV16", "KIV25", "KIV3", "KIV36", "KIV27", "KIV6", "KIV15", "KIV34", "KIV30", "KIV4", "KIV37", "KIV23", "KIV21", "KIV1", "KIV7", "KIV24", "KIV12", "KIV5", "KIV28", "KIV13", "KIV10", "KIV9", "KIV14", "KIV18", "KIV19", "KIV31", "KIV32", "KIV33", "KIV29", "KIV38", "KIV22", "KIV35"], "lib": ["NC Indigent PF sous DIU ou Implant gratuit", "Nouveaux cas TBC + d\u00c3\u00a9pist\u00c3\u00a9s (3 examens crachat)", "Nombre des visites \u00c3\u00a0\u00c2\u00a0 domicile r\u00c3\u00a9alis\u00c3\u00a9es", "Nouveau  cas suivi en observation", "Pilule + Inj (Nouv acceptantes) (si score qualit\u00c3\u00a9 >ou= \u00c3\u00a0\u00c2\u00a0 60%)", "PF Naturelle nouvelles inscrites couples autonomes", "CPN: 2\u00c3\u00a8me visite au 42e jour", "Indigent ayant re\u00c3\u00a7u Implants ou DIU", "Accouchements assist\u00c3\u00a9s avec 3 CPN (si score qualit\u00c3\u00a9 > ou = \u00c3\u00a0\u00c2\u00a0 60%)", "Patients graves r\u00c3\u00a9f\u00c3\u00a9r\u00c3\u00a9s et arriv\u00c3\u00a9 \u00c3\u00a0 l'h\u00c3\u00b4pital", "R\u00c3\u00a9union  d'analyse des donn\u00c3\u00a9es SNIS  y compris les donn\u00c3\u00a9es financi\u00c3\u00a8res  transmis  en annexe du SNIS  au BCZS  et rapport  SSR  transmis chez AAP", "Cas de VVS Refer\u00c3\u00a9s  et arriv\u00c3\u00a9es \u00c3\u00a0\u00c2\u00a0 l'Hopital", "Enfants compl\u00c3\u00a8tement vaccin\u00c3\u00a9s", "PF: Insertion d'implants ou DIU 2% par an", "Nbre des jeunes de 10 \u00c3\u00a0\u00c2\u00a0 24 ans ayant b\u00c3\u00a9n\u00c3\u00a9fici\u00c3\u00a9 le service  SSR", "Nombre d'Accouch\u00c3\u00a9es VIH+ mis sous traitement", "Enfant de 12 \u00c3\u00a0\u00c2\u00a0 59 mois inscrit \u00c3\u00a0\u00c2\u00a0la CPS 2", "R\u00c3\u00a9union  d'analyse des donn\u00c3\u00a9es SNIS  y compris les donn\u00c3\u00a9es financi\u00c3\u00a8res", "CPN 3 visites standards accomplies", "PF. Nombre des cas de Ligature et Vasectomie  r\u00c3\u00a9f\u00c3\u00a9r\u00c3\u00a9s et arriv\u00c3\u00a9 \u00c3\u00a0\u00c2\u00a0 l'h\u00c3\u00b4pital", "Consultations externes", "Femme enceinte ayant re\u00c3\u00a7u VAT 2+", "Accouchements assist\u00c3\u00a9s dans FOSA (si score qualit\u00c3\u00a9 >ou= \u00c3\u00a0\u00c2\u00a0 60%)", "Pilule + Inj (Anc acceptantes) (si score qualit\u00c3\u00a9 >ou= \u00c3\u00a0\u00c2\u00a0 60%)", "Enfant 12 \u00c3\u00a0\u00c2\u00a0 59 mois ayant r\u00c3\u00a9alis\u00c3\u00a9 4 visites standards (1/trim)", "Nombre des femmes enceintes test\u00c3\u00a9es au VIH", "NC Indigent nouvelle utilisatrice (Pillule+Injection)", "Grossesses \u00c3\u00a0\u00c2\u00a0 haut risque r\u00c3\u00a9f\u00c3\u00a9r\u00c3\u00a9e et arriv\u00c3\u00a9e", "Nombre de cas TBC trait\u00c3\u00a9s et BK- apr\u00c3\u00a8s 6 mois", "Indigent Ancienne  utilisatrice PF (Pillule -Injection)", "PF\u00c2\u00a0: Couple ayant adh\u00c3\u00a9r\u00c3\u00a9 aux m\u00c3\u00a9thodes PF modernes", "PF Naturelle nouvelles inscrites", "Nombre des nouveau-n\u00c3\u00a9s des femmes  VIH+ mis sous traitement", "Consultations externes (nvx cas de victime  des violences sexuelles trait\u00c3\u00a9s dans 72h)", "R\u00c3\u00a9unions d'\u00c3\u00a9change avec les jeunes et adolescents de 10 \u00c3\u00a0\u00c2\u00a024 ans organis\u00c3\u00a9 au CS", "Nombre des couples test\u00c3\u00a9s au VIH pour PTME ", "Promptitude, compl\u00c3\u00a9tude et correctitude \u00c3\u00a0\u00c2\u00a0 100% du SNIS transmis au BCZS", "CPN au 4\u00c3\u00a8me mois (d\u00c3\u00a9but T2)", "Nbre des jeunes de 18 \u00c3\u00a0\u00c2\u00a0 24 ans ayant  re\u00c3\u00a7u les contraceptifs modernes"]}, "lib": "Blood transfusion"}, "ETH7": {"matching": {"distances": [28.125, 26.875, null, null, 27.5, null, 40.625, 28.125, 28.125, 27.5, null, null, 26.875, 27.5, null, 27.5, null, null, 40.625, null, 26.875, 40.625, 28.125, 40.0, null, 28.125, 28.125, null, 26.25, 40.625, null, null, 26.875, null, null, 27.5, null, 40.625, null], "indicators": ["KIV17", "KIV8", "KIV39", "KIV2", "KIV11", "KIV20", "KIV26", "KIV16", "KIV25", "KIV3", "KIV36", "KIV27", "KIV6", "KIV15", "KIV34", "KIV30", "KIV4", "KIV37", "KIV23", "KIV21", "KIV1", "KIV7", "KIV24", "KIV12", "KIV5", "KIV28", "KIV13", "KIV10", "KIV9", "KIV14", "KIV18", "KIV19", "KIV31", "KIV32", "KIV33", "KIV29", "KIV38", "KIV22", "KIV35"], "lib": ["NC Indigent PF sous DIU ou Implant gratuit", "Nouveaux cas TBC + d\u00c3\u00a9pist\u00c3\u00a9s (3 examens crachat)", "Nombre des visites \u00c3\u00a0\u00c2\u00a0 domicile r\u00c3\u00a9alis\u00c3\u00a9es", "Nouveau  cas suivi en observation", "Pilule + Inj (Nouv acceptantes) (si score qualit\u00c3\u00a9 >ou= \u00c3\u00a0\u00c2\u00a0 60%)", "PF Naturelle nouvelles inscrites couples autonomes", "CPN: 2\u00c3\u00a8me visite au 42e jour", "Indigent ayant re\u00c3\u00a7u Implants ou DIU", "Accouchements assist\u00c3\u00a9s avec 3 CPN (si score qualit\u00c3\u00a9 > ou = \u00c3\u00a0\u00c2\u00a0 60%)", "Patients graves r\u00c3\u00a9f\u00c3\u00a9r\u00c3\u00a9s et arriv\u00c3\u00a9 \u00c3\u00a0 l'h\u00c3\u00b4pital", "R\u00c3\u00a9union  d'analyse des donn\u00c3\u00a9es SNIS  y compris les donn\u00c3\u00a9es financi\u00c3\u00a8res  transmis  en annexe du SNIS  au BCZS  et rapport  SSR  transmis chez AAP", "Cas de VVS Refer\u00c3\u00a9s  et arriv\u00c3\u00a9es \u00c3\u00a0\u00c2\u00a0 l'Hopital", "Enfants compl\u00c3\u00a8tement vaccin\u00c3\u00a9s", "PF: Insertion d'implants ou DIU 2% par an", "Nbre des jeunes de 10 \u00c3\u00a0\u00c2\u00a0 24 ans ayant b\u00c3\u00a9n\u00c3\u00a9fici\u00c3\u00a9 le service  SSR", "Nombre d'Accouch\u00c3\u00a9es VIH+ mis sous traitement", "Enfant de 12 \u00c3\u00a0\u00c2\u00a0 59 mois inscrit \u00c3\u00a0\u00c2\u00a0la CPS 2", "R\u00c3\u00a9union  d'analyse des donn\u00c3\u00a9es SNIS  y compris les donn\u00c3\u00a9es financi\u00c3\u00a8res", "CPN 3 visites standards accomplies", "PF. Nombre des cas de Ligature et Vasectomie  r\u00c3\u00a9f\u00c3\u00a9r\u00c3\u00a9s et arriv\u00c3\u00a9 \u00c3\u00a0\u00c2\u00a0 l'h\u00c3\u00b4pital", "Consultations externes", "Femme enceinte ayant re\u00c3\u00a7u VAT 2+", "Accouchements assist\u00c3\u00a9s dans FOSA (si score qualit\u00c3\u00a9 >ou= \u00c3\u00a0\u00c2\u00a0 60%)", "Pilule + Inj (Anc acceptantes) (si score qualit\u00c3\u00a9 >ou= \u00c3\u00a0\u00c2\u00a0 60%)", "Enfant 12 \u00c3\u00a0\u00c2\u00a0 59 mois ayant r\u00c3\u00a9alis\u00c3\u00a9 4 visites standards (1/trim)", "Nombre des femmes enceintes test\u00c3\u00a9es au VIH", "NC Indigent nouvelle utilisatrice (Pillule+Injection)", "Grossesses \u00c3\u00a0\u00c2\u00a0 haut risque r\u00c3\u00a9f\u00c3\u00a9r\u00c3\u00a9e et arriv\u00c3\u00a9e", "Nombre de cas TBC trait\u00c3\u00a9s et BK- apr\u00c3\u00a8s 6 mois", "Indigent Ancienne  utilisatrice PF (Pillule -Injection)", "PF\u00c2\u00a0: Couple ayant adh\u00c3\u00a9r\u00c3\u00a9 aux m\u00c3\u00a9thodes PF modernes", "PF Naturelle nouvelles inscrites", "Nombre des nouveau-n\u00c3\u00a9s des femmes  VIH+ mis sous traitement", "Consultations externes (nvx cas de victime  des violences sexuelles trait\u00c3\u00a9s dans 72h)", "R\u00c3\u00a9unions d'\u00c3\u00a9change avec les jeunes et adolescents de 10 \u00c3\u00a0\u00c2\u00a024 ans organis\u00c3\u00a9 au CS", "Nombre des couples test\u00c3\u00a9s au VIH pour PTME ", "Promptitude, compl\u00c3\u00a9tude et correctitude \u00c3\u00a0\u00c2\u00a0 100% du SNIS transmis au BCZS", "CPN au 4\u00c3\u00a8me mois (d\u00c3\u00a9but T2)", "Nbre des jeunes de 18 \u00c3\u00a0\u00c2\u00a0 24 ans ayant  re\u00c3\u00a7u les contraceptifs modernes"]}, "lib": "Severe Acute Malnutrition (SAM) children under five years"}, "ETH4": {"matching": {"distances": [23.88888888888889, 23.333333333333332, null, null, 23.333333333333332, null, 35.0, 23.88888888888889, 23.88888888888889, 23.333333333333332, null, null, 23.88888888888889, 23.333333333333332, null, 24.444444444444443, null, null, 35.0, null, 23.333333333333332, 35.0, 23.88888888888889, 34.44444444444444, null, 24.444444444444443, 23.88888888888889, null, 23.333333333333332, 35.0, null, null, 23.88888888888889, null, null, 23.88888888888889, null, 35.0, null], "indicators": ["KIV17", "KIV8", "KIV39", "KIV2", "KIV11", "KIV20", "KIV26", "KIV16", "KIV25", "KIV3", "KIV36", "KIV27", "KIV6", "KIV15", "KIV34", "KIV30", "KIV4", "KIV37", "KIV23", "KIV21", "KIV1", "KIV7", "KIV24", "KIV12", "KIV5", "KIV28", "KIV13", "KIV10", "KIV9", "KIV14", "KIV18", "KIV19", "KIV31", "KIV32", "KIV33", "KIV29", "KIV38", "KIV22", "KIV35"], "lib": ["NC Indigent PF sous DIU ou Implant gratuit", "Nouveaux cas TBC + d\u00c3\u00a9pist\u00c3\u00a9s (3 examens crachat)", "Nombre des visites \u00c3\u00a0\u00c2\u00a0 domicile r\u00c3\u00a9alis\u00c3\u00a9es", "Nouveau  cas suivi en observation", "Pilule + Inj (Nouv acceptantes) (si score qualit\u00c3\u00a9 >ou= \u00c3\u00a0\u00c2\u00a0 60%)", "PF Naturelle nouvelles inscrites couples autonomes", "CPN: 2\u00c3\u00a8me visite au 42e jour", "Indigent ayant re\u00c3\u00a7u Implants ou DIU", "Accouchements assist\u00c3\u00a9s avec 3 CPN (si score qualit\u00c3\u00a9 > ou = \u00c3\u00a0\u00c2\u00a0 60%)", "Patients graves r\u00c3\u00a9f\u00c3\u00a9r\u00c3\u00a9s et arriv\u00c3\u00a9 \u00c3\u00a0 l'h\u00c3\u00b4pital", "R\u00c3\u00a9union  d'analyse des donn\u00c3\u00a9es SNIS  y compris les donn\u00c3\u00a9es financi\u00c3\u00a8res  transmis  en annexe du SNIS  au BCZS  et rapport  SSR  transmis chez AAP", "Cas de VVS Refer\u00c3\u00a9s  et arriv\u00c3\u00a9es \u00c3\u00a0\u00c2\u00a0 l'Hopital", "Enfants compl\u00c3\u00a8tement vaccin\u00c3\u00a9s", "PF: Insertion d'implants ou DIU 2% par an", "Nbre des jeunes de 10 \u00c3\u00a0\u00c2\u00a0 24 ans ayant b\u00c3\u00a9n\u00c3\u00a9fici\u00c3\u00a9 le service  SSR", "Nombre d'Accouch\u00c3\u00a9es VIH+ mis sous traitement", "Enfant de 12 \u00c3\u00a0\u00c2\u00a0 59 mois inscrit \u00c3\u00a0\u00c2\u00a0la CPS 2", "R\u00c3\u00a9union  d'analyse des donn\u00c3\u00a9es SNIS  y compris les donn\u00c3\u00a9es financi\u00c3\u00a8res", "CPN 3 visites standards accomplies", "PF. Nombre des cas de Ligature et Vasectomie  r\u00c3\u00a9f\u00c3\u00a9r\u00c3\u00a9s et arriv\u00c3\u00a9 \u00c3\u00a0\u00c2\u00a0 l'h\u00c3\u00b4pital", "Consultations externes", "Femme enceinte ayant re\u00c3\u00a7u VAT 2+", "Accouchements assist\u00c3\u00a9s dans FOSA (si score qualit\u00c3\u00a9 >ou= \u00c3\u00a0\u00c2\u00a0 60%)", "Pilule + Inj (Anc acceptantes) (si score qualit\u00c3\u00a9 >ou= \u00c3\u00a0\u00c2\u00a0 60%)", "Enfant 12 \u00c3\u00a0\u00c2\u00a0 59 mois ayant r\u00c3\u00a9alis\u00c3\u00a9 4 visites standards (1/trim)", "Nombre des femmes enceintes test\u00c3\u00a9es au VIH", "NC Indigent nouvelle utilisatrice (Pillule+Injection)", "Grossesses \u00c3\u00a0\u00c2\u00a0 haut risque r\u00c3\u00a9f\u00c3\u00a9r\u00c3\u00a9e et arriv\u00c3\u00a9e", "Nombre de cas TBC trait\u00c3\u00a9s et BK- apr\u00c3\u00a8s 6 mois", "Indigent Ancienne  utilisatrice PF (Pillule -Injection)", "PF\u00c2\u00a0: Couple ayant adh\u00c3\u00a9r\u00c3\u00a9 aux m\u00c3\u00a9thodes PF modernes", "PF Naturelle nouvelles inscrites", "Nombre des nouveau-n\u00c3\u00a9s des femmes  VIH+ mis sous traitement", "Consultations externes (nvx cas de victime  des violences sexuelles trait\u00c3\u00a9s dans 72h)", "R\u00c3\u00a9unions d'\u00c3\u00a9change avec les jeunes et adolescents de 10 \u00c3\u00a0\u00c2\u00a024 ans organis\u00c3\u00a9 au CS", "Nombre des couples test\u00c3\u00a9s au VIH pour PTME ", "Promptitude, compl\u00c3\u00a9tude et correctitude \u00c3\u00a0\u00c2\u00a0 100% du SNIS transmis au BCZS", "CPN au 4\u00c3\u00a8me mois (d\u00c3\u00a9but T2)", "Nbre des jeunes de 18 \u00c3\u00a0\u00c2\u00a0 24 ans ayant  re\u00c3\u00a7u les contraceptifs modernes"]}, "lib": "Major surgery cases (excluding caesarian sections)"}, "ETH10": {"matching": {"distances": [24.444444444444443, 23.88888888888889, null, null, 24.444444444444443, null, 35.55555555555556, 24.444444444444443, 24.444444444444443, 23.88888888888889, null, null, 25.0, 24.444444444444443, null, 12.777777777777779, null, null, 35.55555555555556, null, 23.88888888888889, 35.55555555555556, 24.444444444444443, 35.55555555555556, null, 13.333333333333334, 24.444444444444443, null, 23.333333333333332, 35.55555555555556, null, null, 11.666666666666666, null, null, 12.777777777777779, null, 35.55555555555556, null], "indicators": ["KIV17", "KIV8", "KIV39", "KIV2", "KIV11", "KIV20", "KIV26", "KIV16", "KIV25", "KIV3", "KIV36", "KIV27", "KIV6", "KIV15", "KIV34", "KIV30", "KIV4", "KIV37", "KIV23", "KIV21", "KIV1", "KIV7", "KIV24", "KIV12", "KIV5", "KIV28", "KIV13", "KIV10", "KIV9", "KIV14", "KIV18", "KIV19", "KIV31", "KIV32", "KIV33", "KIV29", "KIV38", "KIV22", "KIV35"], "lib": ["NC Indigent PF sous DIU ou Implant gratuit", "Nouveaux cas TBC + d\u00c3\u00a9pist\u00c3\u00a9s (3 examens crachat)", "Nombre des visites \u00c3\u00a0\u00c2\u00a0 domicile r\u00c3\u00a9alis\u00c3\u00a9es", "Nouveau  cas suivi en observation", "Pilule + Inj (Nouv acceptantes) (si score qualit\u00c3\u00a9 >ou= \u00c3\u00a0\u00c2\u00a0 60%)", "PF Naturelle nouvelles inscrites couples autonomes", "CPN: 2\u00c3\u00a8me visite au 42e jour", "Indigent ayant re\u00c3\u00a7u Implants ou DIU", "Accouchements assist\u00c3\u00a9s avec 3 CPN (si score qualit\u00c3\u00a9 > ou = \u00c3\u00a0\u00c2\u00a0 60%)", "Patients graves r\u00c3\u00a9f\u00c3\u00a9r\u00c3\u00a9s et arriv\u00c3\u00a9 \u00c3\u00a0 l'h\u00c3\u00b4pital", "R\u00c3\u00a9union  d'analyse des donn\u00c3\u00a9es SNIS  y compris les donn\u00c3\u00a9es financi\u00c3\u00a8res  transmis  en annexe du SNIS  au BCZS  et rapport  SSR  transmis chez AAP", "Cas de VVS Refer\u00c3\u00a9s  et arriv\u00c3\u00a9es \u00c3\u00a0\u00c2\u00a0 l'Hopital", "Enfants compl\u00c3\u00a8tement vaccin\u00c3\u00a9s", "PF: Insertion d'implants ou DIU 2% par an", "Nbre des jeunes de 10 \u00c3\u00a0\u00c2\u00a0 24 ans ayant b\u00c3\u00a9n\u00c3\u00a9fici\u00c3\u00a9 le service  SSR", "Nombre d'Accouch\u00c3\u00a9es VIH+ mis sous traitement", "Enfant de 12 \u00c3\u00a0\u00c2\u00a0 59 mois inscrit \u00c3\u00a0\u00c2\u00a0la CPS 2", "R\u00c3\u00a9union  d'analyse des donn\u00c3\u00a9es SNIS  y compris les donn\u00c3\u00a9es financi\u00c3\u00a8res", "CPN 3 visites standards accomplies", "PF. Nombre des cas de Ligature et Vasectomie  r\u00c3\u00a9f\u00c3\u00a9r\u00c3\u00a9s et arriv\u00c3\u00a9 \u00c3\u00a0\u00c2\u00a0 l'h\u00c3\u00b4pital", "Consultations externes", "Femme enceinte ayant re\u00c3\u00a7u VAT 2+", "Accouchements assist\u00c3\u00a9s dans FOSA (si score qualit\u00c3\u00a9 >ou= \u00c3\u00a0\u00c2\u00a0 60%)", "Pilule + Inj (Anc acceptantes) (si score qualit\u00c3\u00a9 >ou= \u00c3\u00a0\u00c2\u00a0 60%)", "Enfant 12 \u00c3\u00a0\u00c2\u00a0 59 mois ayant r\u00c3\u00a9alis\u00c3\u00a9 4 visites standards (1/trim)", "Nombre des femmes enceintes test\u00c3\u00a9es au VIH", "NC Indigent nouvelle utilisatrice (Pillule+Injection)", "Grossesses \u00c3\u00a0\u00c2\u00a0 haut risque r\u00c3\u00a9f\u00c3\u00a9r\u00c3\u00a9e et arriv\u00c3\u00a9e", "Nombre de cas TBC trait\u00c3\u00a9s et BK- apr\u00c3\u00a8s 6 mois", "Indigent Ancienne  utilisatrice PF (Pillule -Injection)", "PF\u00c2\u00a0: Couple ayant adh\u00c3\u00a9r\u00c3\u00a9 aux m\u00c3\u00a9thodes PF modernes", "PF Naturelle nouvelles inscrites", "Nombre des nouveau-n\u00c3\u00a9s des femmes  VIH+ mis sous traitement", "Consultations externes (nvx cas de victime  des violences sexuelles trait\u00c3\u00a9s dans 72h)", "R\u00c3\u00a9unions d'\u00c3\u00a9change avec les jeunes et adolescents de 10 \u00c3\u00a0\u00c2\u00a024 ans organis\u00c3\u00a9 au CS", "Nombre des couples test\u00c3\u00a9s au VIH pour PTME ", "Promptitude, compl\u00c3\u00a9tude et correctitude \u00c3\u00a0\u00c2\u00a0 100% du SNIS transmis au BCZS", "CPN au 4\u00c3\u00a8me mois (d\u00c3\u00a9but T2)", "Nbre des jeunes de 18 \u00c3\u00a0\u00c2\u00a0 24 ans ayant  re\u00c3\u00a7u les contraceptifs modernes"]}, "lib": "Newborn management of a baby born to an HIV positive mother"}, "ETH8": {"matching": {"distances": [26.25, 26.25, null, null, 26.25, null, 38.75, 26.25, 26.25, 25.625, null, null, 26.875, 26.25, null, 26.875, null, null, 38.75, null, 26.25, 38.75, 26.25, 38.75, null, 26.875, 26.25, null, 26.25, 38.75, null, null, 26.25, null, null, 26.25, null, 38.75, null], "indicators": ["KIV17", "KIV8", "KIV39", "KIV2", "KIV11", "KIV20", "KIV26", "KIV16", "KIV25", "KIV3", "KIV36", "KIV27", "KIV6", "KIV15", "KIV34", "KIV30", "KIV4", "KIV37", "KIV23", "KIV21", "KIV1", "KIV7", "KIV24", "KIV12", "KIV5", "KIV28", "KIV13", "KIV10", "KIV9", "KIV14", "KIV18", "KIV19", "KIV31", "KIV32", "KIV33", "KIV29", "KIV38", "KIV22", "KIV35"], "lib": ["NC Indigent PF sous DIU ou Implant gratuit", "Nouveaux cas TBC + d\u00c3\u00a9pist\u00c3\u00a9s (3 examens crachat)", "Nombre des visites \u00c3\u00a0\u00c2\u00a0 domicile r\u00c3\u00a9alis\u00c3\u00a9es", "Nouveau  cas suivi en observation", "Pilule + Inj (Nouv acceptantes) (si score qualit\u00c3\u00a9 >ou= \u00c3\u00a0\u00c2\u00a0 60%)", "PF Naturelle nouvelles inscrites couples autonomes", "CPN: 2\u00c3\u00a8me visite au 42e jour", "Indigent ayant re\u00c3\u00a7u Implants ou DIU", "Accouchements assist\u00c3\u00a9s avec 3 CPN (si score qualit\u00c3\u00a9 > ou = \u00c3\u00a0\u00c2\u00a0 60%)", "Patients graves r\u00c3\u00a9f\u00c3\u00a9r\u00c3\u00a9s et arriv\u00c3\u00a9 \u00c3\u00a0 l'h\u00c3\u00b4pital", "R\u00c3\u00a9union  d'analyse des donn\u00c3\u00a9es SNIS  y compris les donn\u00c3\u00a9es financi\u00c3\u00a8res  transmis  en annexe du SNIS  au BCZS  et rapport  SSR  transmis chez AAP", "Cas de VVS Refer\u00c3\u00a9s  et arriv\u00c3\u00a9es \u00c3\u00a0\u00c2\u00a0 l'Hopital", "Enfants compl\u00c3\u00a8tement vaccin\u00c3\u00a9s", "PF: Insertion d'implants ou DIU 2% par an", "Nbre des jeunes de 10 \u00c3\u00a0\u00c2\u00a0 24 ans ayant b\u00c3\u00a9n\u00c3\u00a9fici\u00c3\u00a9 le service  SSR", "Nombre d'Accouch\u00c3\u00a9es VIH+ mis sous traitement", "Enfant de 12 \u00c3\u00a0\u00c2\u00a0 59 mois inscrit \u00c3\u00a0\u00c2\u00a0la CPS 2", "R\u00c3\u00a9union  d'analyse des donn\u00c3\u00a9es SNIS  y compris les donn\u00c3\u00a9es financi\u00c3\u00a8res", "CPN 3 visites standards accomplies", "PF. Nombre des cas de Ligature et Vasectomie  r\u00c3\u00a9f\u00c3\u00a9r\u00c3\u00a9s et arriv\u00c3\u00a9 \u00c3\u00a0\u00c2\u00a0 l'h\u00c3\u00b4pital", "Consultations externes", "Femme enceinte ayant re\u00c3\u00a7u VAT 2+", "Accouchements assist\u00c3\u00a9s dans FOSA (si score qualit\u00c3\u00a9 >ou= \u00c3\u00a0\u00c2\u00a0 60%)", "Pilule + Inj (Anc acceptantes) (si score qualit\u00c3\u00a9 >ou= \u00c3\u00a0\u00c2\u00a0 60%)", "Enfant 12 \u00c3\u00a0\u00c2\u00a0 59 mois ayant r\u00c3\u00a9alis\u00c3\u00a9 4 visites standards (1/trim)", "Nombre des femmes enceintes test\u00c3\u00a9es au VIH", "NC Indigent nouvelle utilisatrice (Pillule+Injection)", "Grossesses \u00c3\u00a0\u00c2\u00a0 haut risque r\u00c3\u00a9f\u00c3\u00a9r\u00c3\u00a9e et arriv\u00c3\u00a9e", "Nombre de cas TBC trait\u00c3\u00a9s et BK- apr\u00c3\u00a8s 6 mois", "Indigent Ancienne  utilisatrice PF (Pillule -Injection)", "PF\u00c2\u00a0: Couple ayant adh\u00c3\u00a9r\u00c3\u00a9 aux m\u00c3\u00a9thodes PF modernes", "PF Naturelle nouvelles inscrites", "Nombre des nouveau-n\u00c3\u00a9s des femmes  VIH+ mis sous traitement", "Consultations externes (nvx cas de victime  des violences sexuelles trait\u00c3\u00a9s dans 72h)", "R\u00c3\u00a9unions d'\u00c3\u00a9change avec les jeunes et adolescents de 10 \u00c3\u00a0\u00c2\u00a024 ans organis\u00c3\u00a9 au CS", "Nombre des couples test\u00c3\u00a9s au VIH pour PTME ", "Promptitude, compl\u00c3\u00a9tude et correctitude \u00c3\u00a0\u00c2\u00a0 100% du SNIS transmis au BCZS", "CPN au 4\u00c3\u00a8me mois (d\u00c3\u00a9but T2)", "Nbre des jeunes de 18 \u00c3\u00a0\u00c2\u00a0 24 ans ayant  re\u00c3\u00a7u les contraceptifs modernes"]}, "lib": "Referred deliveries received from health center"}, "ETH16": {"matching": {"distances": [100.0, 100.0, 100.0, 100.0, 100.0, 100.0, 100.0, 100.0, 100.0, 100.0, 100.0, 100.0, 100.0, 100.0, 100.0, 100.0, 100.0, 100.0, 100.0, 100.0, 100.0, 100.0, 100.0, 100.0, 100.0, 100.0, 100.0, 100.0, 100.0, 100.0, 100.0, 100.0, 100.0, 100.0, 100.0, 100.0, 100.0, 100.0, 100.0], "indicators": ["KIV17", "KIV8", "KIV39", "KIV2", "KIV11", "KIV20", "KIV26", "KIV16", "KIV25", "KIV3", "KIV36", "KIV27", "KIV6", "KIV15", "KIV34", "KIV30", "KIV4", "KIV37", "KIV23", "KIV21", "KIV1", "KIV7", "KIV24", "KIV12", "KIV5", "KIV28", "KIV13", "KIV10", "KIV9", "KIV14", "KIV18", "KIV19", "KIV31", "KIV32", "KIV33", "KIV29", "KIV38", "KIV22", "KIV35"], "lib": ["NC Indigent PF sous DIU ou Implant gratuit", "Nouveaux cas TBC + d\u00c3\u00a9pist\u00c3\u00a9s (3 examens crachat)", "Nombre des visites \u00c3\u00a0\u00c2\u00a0 domicile r\u00c3\u00a9alis\u00c3\u00a9es", "Nouveau  cas suivi en observation", "Pilule + Inj (Nouv acceptantes) (si score qualit\u00c3\u00a9 >ou= \u00c3\u00a0\u00c2\u00a0 60%)", "PF Naturelle nouvelles inscrites couples autonomes", "CPN: 2\u00c3\u00a8me visite au 42e jour", "Indigent ayant re\u00c3\u00a7u Implants ou DIU", "Accouchements assist\u00c3\u00a9s avec 3 CPN (si score qualit\u00c3\u00a9 > ou = \u00c3\u00a0\u00c2\u00a0 60%)", "Patients graves r\u00c3\u00a9f\u00c3\u00a9r\u00c3\u00a9s et arriv\u00c3\u00a9 \u00c3\u00a0 l'h\u00c3\u00b4pital", "R\u00c3\u00a9union  d'analyse des donn\u00c3\u00a9es SNIS  y compris les donn\u00c3\u00a9es financi\u00c3\u00a8res  transmis  en annexe du SNIS  au BCZS  et rapport  SSR  transmis chez AAP", "Cas de VVS Refer\u00c3\u00a9s  et arriv\u00c3\u00a9es \u00c3\u00a0\u00c2\u00a0 l'Hopital", "Enfants compl\u00c3\u00a8tement vaccin\u00c3\u00a9s", "PF: Insertion d'implants ou DIU 2% par an", "Nbre des jeunes de 10 \u00c3\u00a0\u00c2\u00a0 24 ans ayant b\u00c3\u00a9n\u00c3\u00a9fici\u00c3\u00a9 le service  SSR", "Nombre d'Accouch\u00c3\u00a9es VIH+ mis sous traitement", "Enfant de 12 \u00c3\u00a0\u00c2\u00a0 59 mois inscrit \u00c3\u00a0\u00c2\u00a0la CPS 2", "R\u00c3\u00a9union  d'analyse des donn\u00c3\u00a9es SNIS  y compris les donn\u00c3\u00a9es financi\u00c3\u00a8res", "CPN 3 visites standards accomplies", "PF. Nombre des cas de Ligature et Vasectomie  r\u00c3\u00a9f\u00c3\u00a9r\u00c3\u00a9s et arriv\u00c3\u00a9 \u00c3\u00a0\u00c2\u00a0 l'h\u00c3\u00b4pital", "Consultations externes", "Femme enceinte ayant re\u00c3\u00a7u VAT 2+", "Accouchements assist\u00c3\u00a9s dans FOSA (si score qualit\u00c3\u00a9 >ou= \u00c3\u00a0\u00c2\u00a0 60%)", "Pilule + Inj (Anc acceptantes) (si score qualit\u00c3\u00a9 >ou= \u00c3\u00a0\u00c2\u00a0 60%)", "Enfant 12 \u00c3\u00a0\u00c2\u00a0 59 mois ayant r\u00c3\u00a9alis\u00c3\u00a9 4 visites standards (1/trim)", "Nombre des femmes enceintes test\u00c3\u00a9es au VIH", "NC Indigent nouvelle utilisatrice (Pillule+Injection)", "Grossesses \u00c3\u00a0\u00c2\u00a0 haut risque r\u00c3\u00a9f\u00c3\u00a9r\u00c3\u00a9e et arriv\u00c3\u00a9e", "Nombre de cas TBC trait\u00c3\u00a9s et BK- apr\u00c3\u00a8s 6 mois", "Indigent Ancienne  utilisatrice PF (Pillule -Injection)", "PF\u00c2\u00a0: Couple ayant adh\u00c3\u00a9r\u00c3\u00a9 aux m\u00c3\u00a9thodes PF modernes", "PF Naturelle nouvelles inscrites", "Nombre des nouveau-n\u00c3\u00a9s des femmes  VIH+ mis sous traitement", "Consultations externes (nvx cas de victime  des violences sexuelles trait\u00c3\u00a9s dans 72h)", "R\u00c3\u00a9unions d'\u00c3\u00a9change avec les jeunes et adolescents de 10 \u00c3\u00a0\u00c2\u00a024 ans organis\u00c3\u00a9 au CS", "Nombre des couples test\u00c3\u00a9s au VIH pour PTME ", "Promptitude, compl\u00c3\u00a9tude et correctitude \u00c3\u00a0\u00c2\u00a0 100% du SNIS transmis au BCZS", "CPN au 4\u00c3\u00a8me mois (d\u00c3\u00a9but T2)", "Nbre des jeunes de 18 \u00c3\u00a0\u00c2\u00a0 24 ans ayant  re\u00c3\u00a7u les contraceptifs modernes"]}, "lib": "First and repeated visits for FP modern methods (short term)"}, "ETH17": {"matching": {"distances": [100.0, 100.0, 100.0, 100.0, 100.0, 100.0, 100.0, 100.0, 100.0, 100.0, 100.0, 100.0, 100.0, 100.0, 100.0, 100.0, 100.0, 100.0, 100.0, 100.0, 100.0, 100.0, 100.0, 100.0, 100.0, 100.0, 100.0, 100.0, 100.0, 100.0, 100.0, 100.0, 100.0, 100.0, 100.0, 100.0, 100.0, 100.0, 100.0], "indicators": ["KIV17", "KIV8", "KIV39", "KIV2", "KIV11", "KIV20", "KIV26", "KIV16", "KIV25", "KIV3", "KIV36", "KIV27", "KIV6", "KIV15", "KIV34", "KIV30", "KIV4", "KIV37", "KIV23", "KIV21", "KIV1", "KIV7", "KIV24", "KIV12", "KIV5", "KIV28", "KIV13", "KIV10", "KIV9", "KIV14", "KIV18", "KIV19", "KIV31", "KIV32", "KIV33", "KIV29", "KIV38", "KIV22", "KIV35"], "lib": ["NC Indigent PF sous DIU ou Implant gratuit", "Nouveaux cas TBC + d\u00c3\u00a9pist\u00c3\u00a9s (3 examens crachat)", "Nombre des visites \u00c3\u00a0\u00c2\u00a0 domicile r\u00c3\u00a9alis\u00c3\u00a9es", "Nouveau  cas suivi en observation", "Pilule + Inj (Nouv acceptantes) (si score qualit\u00c3\u00a9 >ou= \u00c3\u00a0\u00c2\u00a0 60%)", "PF Naturelle nouvelles inscrites couples autonomes", "CPN: 2\u00c3\u00a8me visite au 42e jour", "Indigent ayant re\u00c3\u00a7u Implants ou DIU", "Accouchements assist\u00c3\u00a9s avec 3 CPN (si score qualit\u00c3\u00a9 > ou = \u00c3\u00a0\u00c2\u00a0 60%)", "Patients graves r\u00c3\u00a9f\u00c3\u00a9r\u00c3\u00a9s et arriv\u00c3\u00a9 \u00c3\u00a0 l'h\u00c3\u00b4pital", "R\u00c3\u00a9union  d'analyse des donn\u00c3\u00a9es SNIS  y compris les donn\u00c3\u00a9es financi\u00c3\u00a8res  transmis  en annexe du SNIS  au BCZS  et rapport  SSR  transmis chez AAP", "Cas de VVS Refer\u00c3\u00a9s  et arriv\u00c3\u00a9es \u00c3\u00a0\u00c2\u00a0 l'Hopital", "Enfants compl\u00c3\u00a8tement vaccin\u00c3\u00a9s", "PF: Insertion d'implants ou DIU 2% par an", "Nbre des jeunes de 10 \u00c3\u00a0\u00c2\u00a0 24 ans ayant b\u00c3\u00a9n\u00c3\u00a9fici\u00c3\u00a9 le service  SSR", "Nombre d'Accouch\u00c3\u00a9es VIH+ mis sous traitement", "Enfant de 12 \u00c3\u00a0\u00c2\u00a0 59 mois inscrit \u00c3\u00a0\u00c2\u00a0la CPS 2", "R\u00c3\u00a9union  d'analyse des donn\u00c3\u00a9es SNIS  y compris les donn\u00c3\u00a9es financi\u00c3\u00a8res", "CPN 3 visites standards accomplies", "PF. Nombre des cas de Ligature et Vasectomie  r\u00c3\u00a9f\u00c3\u00a9r\u00c3\u00a9s et arriv\u00c3\u00a9 \u00c3\u00a0\u00c2\u00a0 l'h\u00c3\u00b4pital", "Consultations externes", "Femme enceinte ayant re\u00c3\u00a7u VAT 2+", "Accouchements assist\u00c3\u00a9s dans FOSA (si score qualit\u00c3\u00a9 >ou= \u00c3\u00a0\u00c2\u00a0 60%)", "Pilule + Inj (Anc acceptantes) (si score qualit\u00c3\u00a9 >ou= \u00c3\u00a0\u00c2\u00a0 60%)", "Enfant 12 \u00c3\u00a0\u00c2\u00a0 59 mois ayant r\u00c3\u00a9alis\u00c3\u00a9 4 visites standards (1/trim)", "Nombre des femmes enceintes test\u00c3\u00a9es au VIH", "NC Indigent nouvelle utilisatrice (Pillule+Injection)", "Grossesses \u00c3\u00a0\u00c2\u00a0 haut risque r\u00c3\u00a9f\u00c3\u00a9r\u00c3\u00a9e et arriv\u00c3\u00a9e", "Nombre de cas TBC trait\u00c3\u00a9s et BK- apr\u00c3\u00a8s 6 mois", "Indigent Ancienne  utilisatrice PF (Pillule -Injection)", "PF\u00c2\u00a0: Couple ayant adh\u00c3\u00a9r\u00c3\u00a9 aux m\u00c3\u00a9thodes PF modernes", "PF Naturelle nouvelles inscrites", "Nombre des nouveau-n\u00c3\u00a9s des femmes  VIH+ mis sous traitement", "Consultations externes (nvx cas de victime  des violences sexuelles trait\u00c3\u00a9s dans 72h)", "R\u00c3\u00a9unions d'\u00c3\u00a9change avec les jeunes et adolescents de 10 \u00c3\u00a0\u00c2\u00a024 ans organis\u00c3\u00a9 au CS", "Nombre des couples test\u00c3\u00a9s au VIH pour PTME ", "Promptitude, compl\u00c3\u00a9tude et correctitude \u00c3\u00a0\u00c2\u00a0 100% du SNIS transmis au BCZS", "CPN au 4\u00c3\u00a8me mois (d\u00c3\u00a9but T2)", "Nbre des jeunes de 18 \u00c3\u00a0\u00c2\u00a0 24 ans ayant  re\u00c3\u00a7u les contraceptifs modernes"]}, "lib": "First and repeated visits for FP modern methods (long term)"}, "ETH2": {"matching": {"distances": [25.555555555555557, 24.444444444444443, null, null, 25.0, null, 36.666666666666664, 25.555555555555557, 25.555555555555557, 13.88888888888889, null, null, 24.444444444444443, 25.0, null, 25.555555555555557, null, null, 36.666666666666664, null, 12.222222222222221, 36.666666666666664, 25.555555555555557, 36.111111111111114, null, 25.555555555555557, 25.555555555555557, null, 24.444444444444443, 36.666666666666664, null, null, 25.0, null, null, 25.0, null, 36.666666666666664, null], "indicators": ["KIV17", "KIV8", "KIV39", "KIV2", "KIV11", "KIV20", "KIV26", "KIV16", "KIV25", "KIV3", "KIV36", "KIV27", "KIV6", "KIV15", "KIV34", "KIV30", "KIV4", "KIV37", "KIV23", "KIV21", "KIV1", "KIV7", "KIV24", "KIV12", "KIV5", "KIV28", "KIV13", "KIV10", "KIV9", "KIV14", "KIV18", "KIV19", "KIV31", "KIV32", "KIV33", "KIV29", "KIV38", "KIV22", "KIV35"], "lib": ["NC Indigent PF sous DIU ou Implant gratuit", "Nouveaux cas TBC + d\u00c3\u00a9pist\u00c3\u00a9s (3 examens crachat)", "Nombre des visites \u00c3\u00a0\u00c2\u00a0 domicile r\u00c3\u00a9alis\u00c3\u00a9es", "Nouveau  cas suivi en observation", "Pilule + Inj (Nouv acceptantes) (si score qualit\u00c3\u00a9 >ou= \u00c3\u00a0\u00c2\u00a0 60%)", "PF Naturelle nouvelles inscrites couples autonomes", "CPN: 2\u00c3\u00a8me visite au 42e jour", "Indigent ayant re\u00c3\u00a7u Implants ou DIU", "Accouchements assist\u00c3\u00a9s avec 3 CPN (si score qualit\u00c3\u00a9 > ou = \u00c3\u00a0\u00c2\u00a0 60%)", "Patients graves r\u00c3\u00a9f\u00c3\u00a9r\u00c3\u00a9s et arriv\u00c3\u00a9 \u00c3\u00a0 l'h\u00c3\u00b4pital", "R\u00c3\u00a9union  d'analyse des donn\u00c3\u00a9es SNIS  y compris les donn\u00c3\u00a9es financi\u00c3\u00a8res  transmis  en annexe du SNIS  au BCZS  et rapport  SSR  transmis chez AAP", "Cas de VVS Refer\u00c3\u00a9s  et arriv\u00c3\u00a9es \u00c3\u00a0\u00c2\u00a0 l'Hopital", "Enfants compl\u00c3\u00a8tement vaccin\u00c3\u00a9s", "PF: Insertion d'implants ou DIU 2% par an", "Nbre des jeunes de 10 \u00c3\u00a0\u00c2\u00a0 24 ans ayant b\u00c3\u00a9n\u00c3\u00a9fici\u00c3\u00a9 le service  SSR", "Nombre d'Accouch\u00c3\u00a9es VIH+ mis sous traitement", "Enfant de 12 \u00c3\u00a0\u00c2\u00a0 59 mois inscrit \u00c3\u00a0\u00c2\u00a0la CPS 2", "R\u00c3\u00a9union  d'analyse des donn\u00c3\u00a9es SNIS  y compris les donn\u00c3\u00a9es financi\u00c3\u00a8res", "CPN 3 visites standards accomplies", "PF. Nombre des cas de Ligature et Vasectomie  r\u00c3\u00a9f\u00c3\u00a9r\u00c3\u00a9s et arriv\u00c3\u00a9 \u00c3\u00a0\u00c2\u00a0 l'h\u00c3\u00b4pital", "Consultations externes", "Femme enceinte ayant re\u00c3\u00a7u VAT 2+", "Accouchements assist\u00c3\u00a9s dans FOSA (si score qualit\u00c3\u00a9 >ou= \u00c3\u00a0\u00c2\u00a0 60%)", "Pilule + Inj (Anc acceptantes) (si score qualit\u00c3\u00a9 >ou= \u00c3\u00a0\u00c2\u00a0 60%)", "Enfant 12 \u00c3\u00a0\u00c2\u00a0 59 mois ayant r\u00c3\u00a9alis\u00c3\u00a9 4 visites standards (1/trim)", "Nombre des femmes enceintes test\u00c3\u00a9es au VIH", "NC Indigent nouvelle utilisatrice (Pillule+Injection)", "Grossesses \u00c3\u00a0\u00c2\u00a0 haut risque r\u00c3\u00a9f\u00c3\u00a9r\u00c3\u00a9e et arriv\u00c3\u00a9e", "Nombre de cas TBC trait\u00c3\u00a9s et BK- apr\u00c3\u00a8s 6 mois", "Indigent Ancienne  utilisatrice PF (Pillule -Injection)", "PF\u00c2\u00a0: Couple ayant adh\u00c3\u00a9r\u00c3\u00a9 aux m\u00c3\u00a9thodes PF modernes", "PF Naturelle nouvelles inscrites", "Nombre des nouveau-n\u00c3\u00a9s des femmes  VIH+ mis sous traitement", "Consultations externes (nvx cas de victime  des violences sexuelles trait\u00c3\u00a9s dans 72h)", "R\u00c3\u00a9unions d'\u00c3\u00a9change avec les jeunes et adolescents de 10 \u00c3\u00a0\u00c2\u00a024 ans organis\u00c3\u00a9 au CS", "Nombre des couples test\u00c3\u00a9s au VIH pour PTME ", "Promptitude, compl\u00c3\u00a9tude et correctitude \u00c3\u00a0\u00c2\u00a0 100% du SNIS transmis au BCZS", "CPN au 4\u00c3\u00a8me mois (d\u00c3\u00a9but T2)", "Nbre des jeunes de 18 \u00c3\u00a0\u00c2\u00a0 24 ans ayant  re\u00c3\u00a7u les contraceptifs modernes"]}, "lib": "Out Patient Consultations for children under five years (new cases)"}}